{
  "request": {
    "method": "GET",
    "headers": {},
    "urlPath": "/community-api/secure/offenders/crn/X009923/convictions",
    "queryParameters": {
      "activeOnly": {
        "equalTo": "true"
      }
    }
  },
  "response": {
    "status": 200,
    "headers": {
      "Content-Type": "application/json;charset=UTF-8"
    },
    "jsonBody": [
      {
        "convictionId": 100,
        "index": "12434",
        "active": true,
        "convictionDate": "2020-02-05",
        "referralDate": "2020-09-16",
        "offences": [
          {
            "mainOffence": true,
            "detail": {
              "mainCategoryDescription": "Betting, Gaming and Lotteries (Indictable)",
              "subCategoryDescription": "Cheats at gambling or enables or assists person to cheat (Gambling Act 2005)"
            },
            "offenceDate": "2021-02-01T00:00:00",
            "offenceCount": 1
          },
          {
            "mainOffence": false,
            "detail": {
              "mainCategoryDescription": "Assault on Police Officer",
              "subCategoryDescription": "Assault on Police Officer"
            },
            "offenceDate": "2019-09-09T00:00:00",
            "offenceCount": 1
          }
        ],
        "inBreach": false,
        "failureToComplyCount": 0,
        "breachEnd": null,
        "sentence": {
          "sentenceId": 13710,
          "description": "CJA Community Order",
          "originalLength": 12,
          "originalLengthUnits": "Months",
          "defaultLength": 12,
          "lengthInDays": 364,
          "expectedSentenceEndDate": "2021-02-16",
          "startDate": "2020-02-17",
          "terminationDate": null,
          "terminationReason": null,
          "sentenceType": {
            "code": "SP",
            "description": "ORA Community Order"
          },
          "additionalSentences": [
            {
              "type": {
                "description": "Fine"
              },
              "amount": 500,
              "notes": "£500 fine"
            },
            {
              "type": {
                "description": "Disqualified from Driving"
              },
              "length": 6,
              "notes": null
            }
          ],
          "failureToComplyLimit": 3
        },
        "latestCourtAppearanceOutcome": {
          "code": "6iy",
          "description": "Concrete"
        },
        "responsibleCourt": {
          "courtId": 91295,
          "code": "ext9k",
          "selectable": true,
          "courtName": "Sheffield Magistrates Court",
          "telephoneNumber": "(712) 697-9959 x214",
          "fax": "1-799-883-4097",
          "buildingName": "quasi excepturi et",
          "town": "New Dianaview",
          "county": "Berkshire",
          "postcode": "02650-0534",
          "country": "Namibia",
          "courtTypeId": 4822,
          "createdDatetime": "2020-10-26T01:54:57.487Z",
          "lastUpdatedDatetime": "2020-09-12T13:45:49.488Z",
          "probationAreaId": 46782,
          "probationArea": {
            "code": "nnn",
            "description": "Dewaynestad"
          },
          "courtType": {
            "code": "5ra",
            "description": "Metal"
          }
        },
        "courtAppearance": {
          "courtAppearanceId": 10435,
          "appearanceDate": "2020-12-27",
          "courtCode": "ph2nw",
          "courtName": "Nottingham Crown Court",
          "appearanceType": {
            "code": "33",
            "description": "Concrete"
          },
          "crn": "F402294"
        }
      }
    ]
  },
  "priority": 1
}
