{
  "request": {
    "method": "GET",
    "headers": {},
    "urlPath": "/community-api/secure/offenders/crn/X009923/personalContacts"
  },
  "response": {
    "status": 200,
    "headers": {
      "Content-Type": "application/json;charset=UTF-8"
    },
    "jsonBody": [
      {
        "personalContactId": 49408,
        "title": "Dr",
        "firstName": "Pippa",
        "otherNames": "a",
        "surname": "Wade",
        "previousSurname": "Beer",
        "relationship": "Wife",
        "gender": "Female",
        "relationshipType": {
          "code": "NK",
          "description": "Next of Kin"
        },
        "startDate": "2019-09-13T00:00:00",
        "createdDatetime": "2019-09-13T00:00:00",
        "lastUpdatedDatetime": "2019-09-13T00:00:00",
        "emailAddress": "Carli.Christiansen55@hotmail.com",
        "mobileNumber": "07700 900 141",
        "notes": "Divorced",
        "address": {
          "addressNumber": "64",
          "streetName": "Ermin Street",
          "buildingName": null,
          "town": "Wrenthorpe",
          "county": "West Yorkshire",
          "postcode": "WF2 8WT",
          "telephoneNumber": "07073735801"
        }
      },
      {
        "personalContactId": 29016,
        "title": "Mr",
        "firstName": "Jonathon",
        "otherNames": "a",
        "surname": "Bacon",
        "previousSurname": "Quigley",
        "relationship": "Father",
        "gender": "Male",
        "relationshipType": {
          "code": "NK",
          "description": "Family member"
        },
        "startDate": "2019-09-13T00:00:00",
        "createdDatetime": "2019-09-13T00:00:00",
        "lastUpdatedDatetime": "2019-09-13T00:00:00",
        "emailAddress": "Keshawn_Dooley@gmail.com",
        "mobileNumber": "1-836-781-4311 x324",
        "notes": "Quisquam voluptas quia doloribus.",
        "address": {
          "addressNumber": "70694",
          "streetName": "Kutch Throughway",
          "buildingName": "Movies",
          "town": "Kunzeland",
          "county": "Bedfordshire",
          "postcode": "24124-3156",
          "telephoneNumber": "728.696.1897 x4766"
        }
      }
    ]
  }
}
